<annotation>
	<folder>dataku</folder>
	<filename>20211207_081557.jpg</filename>
	<path>C:\Users\husin\Documents\Coding\Kuliah\Viskom\tugas-4\dataku\20211207_081557.jpg</path>
	<source>
		<database>Unknown</database>
	</source>
	<size>
		<width>2160</width>
		<height>2160</height>
		<depth>3</depth>
	</size>
	<segmented>0</segmented>
	<object>
		<name>num4</name>
		<pose>Unspecified</pose>
		<truncated>0</truncated>
		<difficult>0</difficult>
		<bndbox>
			<xmin>161</xmin>
			<ymin>899</ymin>
			<xmax>357</xmax>
			<ymax>1226</ymax>
		</bndbox>
	</object>
	<object>
		<name>sum</name>
		<pose>Unspecified</pose>
		<truncated>0</truncated>
		<difficult>0</difficult>
		<bndbox>
			<xmin>432</xmin>
			<ymin>892</ymin>
			<xmax>648</xmax>
			<ymax>1173</ymax>
		</bndbox>
	</object>
	<object>
		<name>num3</name>
		<pose>Unspecified</pose>
		<truncated>0</truncated>
		<difficult>0</difficult>
		<bndbox>
			<xmin>702</xmin>
			<ymin>913</ymin>
			<xmax>896</xmax>
			<ymax>1141</ymax>
		</bndbox>
	</object>
	<object>
		<name>lessthan-equal</name>
		<pose>Unspecified</pose>
		<truncated>0</truncated>
		<difficult>0</difficult>
		<bndbox>
			<xmin>1067</xmin>
			<ymin>905</ymin>
			<xmax>1352</xmax>
			<ymax>1195</ymax>
		</bndbox>
	</object>
	<object>
		<name>num5</name>
		<pose>Unspecified</pose>
		<truncated>0</truncated>
		<difficult>0</difficult>
		<bndbox>
			<xmin>1450</xmin>
			<ymin>874</ymin>
			<xmax>1675</xmax>
			<ymax>1128</ymax>
		</bndbox>
	</object>
	<object>
		<name>min</name>
		<pose>Unspecified</pose>
		<truncated>0</truncated>
		<difficult>0</difficult>
		<bndbox>
			<xmin>1677</xmin>
			<ymin>947</ymin>
			<xmax>1855</xmax>
			<ymax>1045</ymax>
		</bndbox>
	</object>
	<object>
		<name>num3</name>
		<pose>Unspecified</pose>
		<truncated>0</truncated>
		<difficult>0</difficult>
		<bndbox>
			<xmin>1862</xmin>
			<ymin>886</ymin>
			<xmax>2034</xmax>
			<ymax>1111</ymax>
		</bndbox>
	</object>
</annotation>
