<annotation>
	<folder>foto viskom</folder>
	<filename>IMG_20211206_163128.jpg</filename>
	<path>D:\foto viskom\IMG_20211206_163128.jpg</path>
	<source>
		<database>Unknown</database>
	</source>
	<size>
		<width>4000</width>
		<height>4000</height>
		<depth>3</depth>
	</size>
	<segmented>0</segmented>
	<object>
		<name>num5</name>
		<pose>Unspecified</pose>
		<truncated>0</truncated>
		<difficult>0</difficult>
		<bndbox>
			<xmin>841</xmin>
			<ymin>996</ymin>
			<xmax>1410</xmax>
			<ymax>1587</ymax>
		</bndbox>
	</object>
	<object>
		<name>num5</name>
		<pose>Unspecified</pose>
		<truncated>0</truncated>
		<difficult>0</difficult>
		<bndbox>
			<xmin>1663</xmin>
			<ymin>1187</ymin>
			<xmax>2002</xmax>
			<ymax>1782</ymax>
		</bndbox>
	</object>
	<object>
		<name>num5</name>
		<pose>Unspecified</pose>
		<truncated>0</truncated>
		<difficult>0</difficult>
		<bndbox>
			<xmin>2119</xmin>
			<ymin>1304</ymin>
			<xmax>2432</xmax>
			<ymax>1848</ymax>
		</bndbox>
	</object>
	<object>
		<name>num5</name>
		<pose>Unspecified</pose>
		<truncated>0</truncated>
		<difficult>0</difficult>
		<bndbox>
			<xmin>2502</xmin>
			<ymin>1448</ymin>
			<xmax>2780</xmax>
			<ymax>1917</ymax>
		</bndbox>
	</object>
	<object>
		<name>num5</name>
		<pose>Unspecified</pose>
		<truncated>0</truncated>
		<difficult>0</difficult>
		<bndbox>
			<xmin>849</xmin>
			<ymin>1691</ymin>
			<xmax>1336</xmax>
			<ymax>2326</ymax>
		</bndbox>
	</object>
	<object>
		<name>num5</name>
		<pose>Unspecified</pose>
		<truncated>0</truncated>
		<difficult>0</difficult>
		<bndbox>
			<xmin>1649</xmin>
			<ymin>1796</ymin>
			<xmax>2010</xmax>
			<ymax>2348</ymax>
		</bndbox>
	</object>
	<object>
		<name>num5</name>
		<pose>Unspecified</pose>
		<truncated>0</truncated>
		<difficult>0</difficult>
		<bndbox>
			<xmin>2176</xmin>
			<ymin>1904</ymin>
			<xmax>2432</xmax>
			<ymax>2382</ymax>
		</bndbox>
	</object>
	<object>
		<name>num5</name>
		<pose>Unspecified</pose>
		<truncated>0</truncated>
		<difficult>0</difficult>
		<bndbox>
			<xmin>2610</xmin>
			<ymin>1969</ymin>
			<xmax>2823</xmax>
			<ymax>2378</ymax>
		</bndbox>
	</object>
	<object>
		<name>num5</name>
		<pose>Unspecified</pose>
		<truncated>0</truncated>
		<difficult>0</difficult>
		<bndbox>
			<xmin>693</xmin>
			<ymin>2391</ymin>
			<xmax>1323</xmax>
			<ymax>3004</ymax>
		</bndbox>
	</object>
	<object>
		<name>num5</name>
		<pose>Unspecified</pose>
		<truncated>0</truncated>
		<difficult>0</difficult>
		<bndbox>
			<xmin>1689</xmin>
			<ymin>2400</ymin>
			<xmax>1976</xmax>
			<ymax>2882</ymax>
		</bndbox>
	</object>
	<object>
		<name>num5</name>
		<pose>Unspecified</pose>
		<truncated>0</truncated>
		<difficult>0</difficult>
		<bndbox>
			<xmin>2180</xmin>
			<ymin>2409</ymin>
			<xmax>2449</xmax>
			<ymax>2874</ymax>
		</bndbox>
	</object>
	<object>
		<name>num5</name>
		<pose>Unspecified</pose>
		<truncated>0</truncated>
		<difficult>0</difficult>
		<bndbox>
			<xmin>2606</xmin>
			<ymin>2435</ymin>
			<xmax>2845</xmax>
			<ymax>2809</ymax>
		</bndbox>
	</object>
</annotation>
