<annotation>
	<folder>kurang</folder>
	<filename>IMG_20211207_062404.jpg</filename>
	<path>D:\foto viskom\kurang\IMG_20211207_062404.jpg</path>
	<source>
		<database>Unknown</database>
	</source>
	<size>
		<width>3000</width>
		<height>3000</height>
		<depth>3</depth>
	</size>
	<segmented>0</segmented>
	<object>
		<name>num6</name>
		<pose>Unspecified</pose>
		<truncated>0</truncated>
		<difficult>0</difficult>
		<bndbox>
			<xmin>114</xmin>
			<ymin>1264</ymin>
			<xmax>543</xmax>
			<ymax>1825</ymax>
		</bndbox>
	</object>
	<object>
		<name>min</name>
		<pose>Unspecified</pose>
		<truncated>0</truncated>
		<difficult>0</difficult>
		<bndbox>
			<xmin>630</xmin>
			<ymin>1545</ymin>
			<xmax>962</xmax>
			<ymax>1716</ymax>
		</bndbox>
	</object>
	<object>
		<name>num3</name>
		<pose>Unspecified</pose>
		<truncated>0</truncated>
		<difficult>0</difficult>
		<bndbox>
			<xmin>1062</xmin>
			<ymin>1361</ymin>
			<xmax>1559</xmax>
			<ymax>1774</ymax>
		</bndbox>
	</object>
	<object>
		<name>equal</name>
		<pose>Unspecified</pose>
		<truncated>0</truncated>
		<difficult>0</difficult>
		<bndbox>
			<xmin>1736</xmin>
			<ymin>1480</ymin>
			<xmax>2052</xmax>
			<ymax>1745</ymax>
		</bndbox>
	</object>
	<object>
		<name>num3</name>
		<pose>Unspecified</pose>
		<truncated>0</truncated>
		<difficult>0</difficult>
		<bndbox>
			<xmin>2323</xmin>
			<ymin>1296</ymin>
			<xmax>2739</xmax>
			<ymax>1813</ymax>
		</bndbox>
	</object>
</annotation>
