<annotation>
	<folder>Operasi</folder>
	<filename>20211207_060329.jpg</filename>
	<path>C:\Users\ASUS\Documents\Viskom Dataset\Operasi\20211207_060329.jpg</path>
	<source>
		<database>Unknown</database>
	</source>
	<size>
		<width>3088</width>
		<height>3088</height>
		<depth>3</depth>
	</size>
	<segmented>0</segmented>
	<object>
		<name>num6</name>
		<pose>Unspecified</pose>
		<truncated>0</truncated>
		<difficult>0</difficult>
		<bndbox>
			<xmin>247</xmin>
			<ymin>1243</ymin>
			<xmax>808</xmax>
			<ymax>2179</ymax>
		</bndbox>
	</object>
	<object>
		<name>num6</name>
		<pose>Unspecified</pose>
		<truncated>0</truncated>
		<difficult>0</difficult>
		<bndbox>
			<xmin>1176</xmin>
			<ymin>1157</ymin>
			<xmax>1737</xmax>
			<ymax>2093</ymax>
		</bndbox>
	</object>
	<object>
		<name>num6</name>
		<pose>Unspecified</pose>
		<truncated>0</truncated>
		<difficult>0</difficult>
		<bndbox>
			<xmin>2452</xmin>
			<ymin>1103</ymin>
			<xmax>3013</xmax>
			<ymax>2039</ymax>
		</bndbox>
	</object>
	<object>
		<name>multi</name>
		<pose>Unspecified</pose>
		<truncated>0</truncated>
		<difficult>0</difficult>
		<bndbox>
			<xmin>827</xmin>
			<ymin>1543</ymin>
			<xmax>1149</xmax>
			<ymax>1862</ymax>
		</bndbox>
	</object>
	<object>
		<name>equal</name>
		<pose>Unspecified</pose>
		<truncated>0</truncated>
		<difficult>0</difficult>
		<bndbox>
			<xmin>1759</xmin>
			<ymin>1471</ymin>
			<xmax>1991</xmax>
			<ymax>1694</ymax>
		</bndbox>
	</object>
</annotation>
